odoo9_addon_procurement_purchase_no_grouping-9.0.1.0.0-py2.7-nspkg.pth
odoo9_addon_procurement_purchase_no_grouping-9.0.1.0.0.dist-info/DESCRIPTION.rst
odoo9_addon_procurement_purchase_no_grouping-9.0.1.0.0.dist-info/METADATA
odoo9_addon_procurement_purchase_no_grouping-9.0.1.0.0.dist-info/RECORD
odoo9_addon_procurement_purchase_no_grouping-9.0.1.0.0.dist-info/WHEEL
odoo9_addon_procurement_purchase_no_grouping-9.0.1.0.0.dist-info/metadata.json
odoo9_addon_procurement_purchase_no_grouping-9.0.1.0.0.dist-info/namespace_packages.txt
odoo9_addon_procurement_purchase_no_grouping-9.0.1.0.0.dist-info/top_level.txt
odoo_addons/procurement_purchase_no_grouping/README.rst
odoo_addons/procurement_purchase_no_grouping/__init__.py
odoo_addons/procurement_purchase_no_grouping/__openerp__.py
odoo_addons/procurement_purchase_no_grouping/i18n/es.po
odoo_addons/procurement_purchase_no_grouping/i18n/fr.po
odoo_addons/procurement_purchase_no_grouping/i18n/pt_BR.po
odoo_addons/procurement_purchase_no_grouping/i18n/ro.po
odoo_addons/procurement_purchase_no_grouping/i18n/sl.po
odoo_addons/procurement_purchase_no_grouping/models/__init__.py
odoo_addons/procurement_purchase_no_grouping/models/procurement_order.py
odoo_addons/procurement_purchase_no_grouping/models/product_category.py
odoo_addons/procurement_purchase_no_grouping/models/purchase_order.py
odoo_addons/procurement_purchase_no_grouping/tests/__init__.py
odoo_addons/procurement_purchase_no_grouping/tests/test_procurement_purchase_no_grouping.py
odoo_addons/procurement_purchase_no_grouping/views/product_category_view.xml
