Metadata-Version: 2.0
Name: odoo9-addon-procurement-purchase-no-grouping
Version: 9.0.1.0.0
Summary: Procurement Purchase No Grouping
Home-page: https://github.com/OCA/purchase-workflow
Author: AvanzOSC,Tecnativa,Odoo Communtity Association (OCA)
Author-email: UNKNOWN
License: AGPL-3
Platform: UNKNOWN
Classifier: Programming Language :: Python :: 2.7
Classifier: Framework :: Odoo
Classifier: License :: OSI Approved :: GNU Affero General Public License v3
Requires-Dist: odoo (<9.1a,>=9.0a)
